oratools/__init__.py
oratools/cli.py
oratools/tools/__init__.py
oratools/tools/dev_tools.py
oratools/tools/file_tools.py
oratools/tools/image_tools.py
oratools/tools/network_tools.py
oratools/tools/system_tools.py
oratools/tools/youtube_downloader.py
oratools-0.1.0.dist-info/licenses/LICENSE
oratools-0.1.0.dist-info/METADATA
oratools-0.1.0.dist-info/WHEEL
oratools-0.1.0.dist-info/entry_points.txt
oratools-0.1.0.dist-info/top_level.txt
oratools-0.1.0.dist-info/RECORD
